README.rst
setup.py
meepo/__init__.py
meepo/_compat.py
meepo/logutils.py
meepo/pub.py
meepo/replicator.py
meepo/sub.py
meepo/utils.py
meepo.egg-info/PKG-INFO
meepo.egg-info/SOURCES.txt
meepo.egg-info/dependency_links.txt
meepo.egg-info/entry_points.txt
meepo.egg-info/not-zip-safe
meepo.egg-info/requires.txt
meepo.egg-info/top_level.txt
meepo/apps/__init__.py
meepo/apps/mcache.py
meepo/apps/meventsourcing.py
meepo/apps/mnano.py
meepo/apps/mprint.py
meepo/apps/mreplicate.py
meepo/apps/mzdevice.py
meepo/apps/mzmq.py