Metadata-Version: 1.1
Name: meepo
Version: 0.1.8
Summary: event sourcing for databases.
Home-page: https://github.com/eleme/meepo
Author: Lx Yu
Author-email: i@lxyu.net
License: MIT
Keywords: eventsourcing event sourcing replication cache elasticsearch
Platform: UNKNOWN
Classifier: Topic :: Software Development
Classifier: Development Status :: 3 - Alpha
Classifier: Intended Audience :: Developers
Classifier: License :: OSI Approved :: MIT License
Classifier: Programming Language :: Python :: 2.7
Classifier: Programming Language :: Python :: 3.3
Classifier: Programming Language :: Python :: 3.4
